MANIFEST.in
setup.py
socket-server.py
socket_executor/__init__.py
socket_executor.egg-info/PKG-INFO
socket_executor.egg-info/SOURCES.txt
socket_executor.egg-info/dependency_links.txt
socket_executor.egg-info/requires.txt
socket_executor.egg-info/top_level.txt
socket_executor/static/app.css
socket_executor/static/app.js
socket_executor/static/index.html
socket_executor/static/bower_components/angular/.bower.json
socket_executor/static/bower_components/angular/README.md
socket_executor/static/bower_components/angular/angular-csp.css
socket_executor/static/bower_components/angular/angular.js
socket_executor/static/bower_components/angular/angular.min.js
socket_executor/static/bower_components/angular/angular.min.js.gzip
socket_executor/static/bower_components/angular/angular.min.js.map
socket_executor/static/bower_components/angular/bower.json
socket_executor/static/bower_components/angular/package.json
socket_executor/static/bower_components/angular-bootstrap/.bower.json
socket_executor/static/bower_components/angular-bootstrap/bower.json
socket_executor/static/bower_components/angular-bootstrap/ui-bootstrap-tpls.js
socket_executor/static/bower_components/angular-bootstrap/ui-bootstrap-tpls.min.js
socket_executor/static/bower_components/angular-bootstrap/ui-bootstrap.js
socket_executor/static/bower_components/angular-bootstrap/ui-bootstrap.min.js
socket_executor/static/bower_components/angular-scroll-glue/.bower.json
socket_executor/static/bower_components/angular-scroll-glue/README.md
socket_executor/static/bower_components/angular-scroll-glue/bower.json
socket_executor/static/bower_components/angular-scroll-glue/example.html
socket_executor/static/bower_components/angular-scroll-glue/karma.conf.js
socket_executor/static/bower_components/angular-scroll-glue/package.json
socket_executor/static/bower_components/angular-scroll-glue/src/LICENSE
socket_executor/static/bower_components/angular-scroll-glue/src/scrollglue.js
socket_executor/static/bower_components/angular-websocket/.bower.json
socket_executor/static/bower_components/angular-websocket/CHANGELOG.md
socket_executor/static/bower_components/angular-websocket/LICENSE
