Metadata-Version: 1.1
Name: socket_executor
Version: 0.1
Summary: Run scripts with a websocketey wrapper to pipe out the output.
Home-page: https://github.com/hospadar/socket-executor
Author: Luke Hospadaruk
Author-email: luke@hospadaruk.org
License: UNKNOWN
Download-URL: https://github.com/hospadar/socket-executor.git
Platform: UNKNOWN
